rheal/__init__.py
rheal/dggs_classes.py
rhealpix_geo-0.3.0.dist-info/LICENSE
rhealpix_geo-0.3.0.dist-info/WHEEL
rhealpix_geo-0.3.0.dist-info/METADATA
rhealpix_geo-0.3.0.dist-info/RECORD
