Metadata-Version: 2.1
Name: rhealpix-geo
Version: 0.3.0
Summary: Objects for DGGS Cells and collections of Cells.
Home-page: https://github.com/surroundaustralia/rhealpix-geo
License: BSD-3-Clause
Keywords: DGGS,rHEALPix,Geospatial
Author: david-habgood
Author-email: david.habgood@surroundaustralia.com
Maintainer: david-habgood
Maintainer-email: david.habgood@surroundaustralia.com
Requires-Python: >=3.8,<4.0
Classifier: License :: OSI Approved :: BSD License
Classifier: Programming Language :: Python :: 3
Classifier: Programming Language :: Python :: 3.8
Classifier: Programming Language :: Python :: 3.9
Project-URL: Repository, https://github.com/surroundaustralia/rhealpix-geo
